odoo/addons/website_event_filter_selector/README.rst
odoo/addons/website_event_filter_selector/__init__.py
odoo/addons/website_event_filter_selector/__manifest__.py
odoo/addons/website_event_filter_selector/controllers/__init__.py
odoo/addons/website_event_filter_selector/controllers/main.py
odoo/addons/website_event_filter_selector/demo/assets.xml
odoo/addons/website_event_filter_selector/demo/tour_data.xml
odoo/addons/website_event_filter_selector/i18n/de.po
odoo/addons/website_event_filter_selector/i18n/es.po
odoo/addons/website_event_filter_selector/i18n/website_event_filter_selector.pot
odoo/addons/website_event_filter_selector/models/__init__.py
odoo/addons/website_event_filter_selector/models/event.py
odoo/addons/website_event_filter_selector/readme/CONFIGURE.rst
odoo/addons/website_event_filter_selector/readme/CONTRIBUTORS.rst
odoo/addons/website_event_filter_selector/readme/DESCRIPTION.rst
odoo/addons/website_event_filter_selector/readme/ROADMAP.rst
odoo/addons/website_event_filter_selector/static/description/all.png
odoo/addons/website_event_filter_selector/static/description/icon.png
odoo/addons/website_event_filter_selector/static/description/index.html
odoo/addons/website_event_filter_selector/static/src/js/website_event_filter_selector.js
odoo/addons/website_event_filter_selector/static/src/js/website_event_filter_selector.tour.js
odoo/addons/website_event_filter_selector/templates/assets.xml
odoo/addons/website_event_filter_selector/templates/event.xml
odoo/addons/website_event_filter_selector/tests/__init__.py
odoo/addons/website_event_filter_selector/tests/test_ui.py
odoo12_addon_website_event_filter_selector-12.0.1.2.1.dist-info/METADATA
odoo12_addon_website_event_filter_selector-12.0.1.2.1.dist-info/WHEEL
odoo12_addon_website_event_filter_selector-12.0.1.2.1.dist-info/top_level.txt
odoo12_addon_website_event_filter_selector-12.0.1.2.1.dist-info/RECORD
