Metadata-Version: 2.1
Name: odoo12-addon-website-event-filter-selector
Version: 12.0.1.2.1
Summary: Add a customizable top area to filter events with selectors
Home-page: https://github.com/OCA/event
Author: Antiun Ingeniería S.L., Tecnativa, Onestein, Odoo Community Association (OCA)
Author-email: support@odoo-community.org
License: LGPL-3
Platform: UNKNOWN
Classifier: Programming Language :: Python
Classifier: Framework :: Odoo
Classifier: License :: OSI Approved :: GNU Lesser General Public License v3 (LGPLv3)
Requires-Python: >=3.5
Requires-Dist: odoo (<12.1dev,>=12.0a)
